ign8/__init__.py
ign8/aap/__init__.py
ign8/aap/aap.py
ign8/aap/bitbucket.py
ign8/aap/serve.py
ign8/aap/status.py
ign8/airflow/__init__.py
ign8/airflow/airflow.py
ign8/awx/awx_common.py
ign8/awx/awx_credential.py
ign8/awx/awx_executionenvironments.py
ign8/awx/awx_hosts.py
ign8/awx/awx_organisation.py
ign8/awx/awx_project.py
ign8/awx/kalm.py
ign8/bump/__init__.py
ign8/bump/bump.py
ign8/common.py
ign8/dns/__init__.py
ign8/dns/cloudflare.py
ign8/dns/dns.py
ign8/fiile/__init__.py
ign8/fiile/file.py
ign8/gitea/__init__.py
ign8/gitea/git.py
ign8/homeassistant/after.json
ign8/homeassistant/after.lst
ign8/homeassistant/aut.sh
ign8/homeassistant/before.json
ign8/homeassistant/before.lst
ign8/homeassistant/hue.env
ign8/homeassistant/hue.py
ign8/homeassistant/hue.test.py
ign8/homeassistant/logger.py
ign8/homeassistant/os
ign8/homeassistant/paused.conf
ign8/homeassistant/requesttest.py
ign8/homeassistant/requirements.txt
ign8/homeassistant/service.py
ign8/homeassistant/servicetest.py
ign8/homeassistant/start.sh
ign8/homeassistant/stash.py
ign8/homeassistant/test.json
ign8/homeassistant/test.lst
ign8/homeassistant/test.lst.org
ign8/homeassistant/test.sh
ign8/homeassistant/turnontest.py
ign8/iad/__init__.py
ign8/iad/iad.py
ign8/inabox/__init__.py
ign8/inabox/inabox.py
ign8/inabox/virtlib.py
ign8/inthevault/__init__.py
ign8/inthevault/inthevault.py
ign8/jenkins/__init__.py
ign8/jenkins/jenkins.py
ign8/k3s/__init__.py
ign8/k3s/k3s.py
ign8/libsync/animated.gif
ign8/libsync/test.py
ign8/main.py
ign8/netbox/__init__.py
ign8/netbox/netbox.py
ign8/package_data.dat
ign8/passwordstate/__init__.py
ign8/passwordstate/passwordstate.py
ign8/pitv/__init__.py
ign8/pitv/pitv.py
ign8/podman/__init__.py
ign8/podman/podman.py
ign8/podman/serve.py
ign8/pypi/__init__.py
ign8/pypi/pypi.py
ign8/selinux/README.md
ign8/selinux/__init__.py
ign8/selinux/ansible.cfg
ign8/selinux/files/seinfo.sh
ign8/selinux/files/selinuxstatus.sh
ign8/selinux/files/testevent.py
ign8/selinux/files/testsetrouble.py
ign8-4.12.172.dist-info/LICENSE.txt
ign8-4.12.172.dist-info/METADATA
ign8-4.12.172.dist-info/WHEEL
ign8-4.12.172.dist-info/entry_points.txt
ign8-4.12.172.dist-info/RECORD
