Metadata-Version: 2.1
Name: ign8
Version: 4.12.172
Summary: Ignite it all.
Home-page: https://ign8.openknowit.com
License: MIT
Author: Jakob Holst
Author-email: jakob.holst@knowit.dk
Requires-Python: >=3.10,<4.0
Classifier: License :: OSI Approved :: MIT License
Classifier: Programming Language :: Python :: 3
Classifier: Programming Language :: Python :: 3.10
Classifier: Programming Language :: Python :: 3.11
Classifier: Programming Language :: Python :: 3.12
Requires-Dist: CacheControl (>=0.14.0,<0.15.0)
Requires-Dist: Django (>=5.0.6,<6.0.0)
Requires-Dist: Pygments (>=2.18.0,<3.0.0)
Requires-Dist: SecretStorage (>=3.3.3,<4.0.0)
Requires-Dist: asgiref (>=3.8.1,<4.0.0)
Requires-Dist: build (>=1.2.1,<2.0.0)
Requires-Dist: certifi (>=2024.7.4,<2025.0.0)
Requires-Dist: cffi (>=1.16.0,<2.0.0)
Requires-Dist: charset-normalizer (>=3.3.2,<4.0.0)
Requires-Dist: cleo (>=2.1.0,<3.0.0)
Requires-Dist: crashtest (>=0.4.1,<0.5.0)
Requires-Dist: cryptography (>=42.0.8,<43.0.0)
Requires-Dist: distlib (>=0.3.8,<0.4.0)
Requires-Dist: docutils (>=0.21.2,<0.22.0)
Requires-Dist: dulwich (>=0.21.7,<0.22.0)
Requires-Dist: fastjsonschema (>=2.20.0,<3.0.0)
Requires-Dist: filelock (>=3.15.4,<4.0.0)
Requires-Dist: idna (>=3.7,<4.0)
Requires-Dist: importlib_metadata (>=8.0.0,<9.0.0)
Requires-Dist: installer (>=0.7.0,<0.8.0)
Requires-Dist: jeepney (>=0.8.0,<0.9.0)
Requires-Dist: keyring (>=24.3.1,<25.0.0)
Requires-Dist: markdown-it-py (>=3.0.0,<4.0.0)
Requires-Dist: mdurl (>=0.1.2,<0.2.0)
Requires-Dist: more-itertools (>=10.3.0,<11.0.0)
Requires-Dist: msgpack (>=1.0.8,<2.0.0)
Requires-Dist: nh3 (>=0.2.17,<0.3.0)
Requires-Dist: packaging (>=24.1,<25.0)
Requires-Dist: pexpect (>=4.9.0,<5.0.0)
Requires-Dist: pkginfo (>=1.10.0,<2.0.0)
Requires-Dist: platformdirs (>=4.2.2,<5.0.0)
Requires-Dist: poetry (>=1.8.3,<2.0.0)
Requires-Dist: poetry-core (>=1.9.0,<2.0.0)
Requires-Dist: poetry-plugin-export (>=1.8.0,<2.0.0)
Requires-Dist: ptyprocess (>=0.7.0,<0.8.0)
Requires-Dist: pycparser (>=2.22,<3.0)
Requires-Dist: pyproject_hooks (>=1.1.0,<2.0.0)
Requires-Dist: rapidfuzz (>=3.9.4,<4.0.0)
Requires-Dist: readme_renderer (>=43.0,<44.0)
Requires-Dist: requests (>=2.32.3,<3.0.0)
Requires-Dist: requests-toolbelt (>=1.0.0,<2.0.0)
Requires-Dist: rfc3986 (>=2.0.0,<3.0.0)
Requires-Dist: rich (>=13.7.1,<14.0.0)
Requires-Dist: shellingham (>=1.5.4,<2.0.0)
Requires-Dist: sqlparse (>=0.5.0,<0.6.0)
Requires-Dist: tomlkit (>=0.12.5,<0.13.0)
Requires-Dist: trove-classifiers (>=2024.7.2,<2025.0.0)
Requires-Dist: twine (>=5.1.1,<6.0.0)
Requires-Dist: urllib3 (>=2.2.2,<3.0.0)
Requires-Dist: virtualenv (>=20.26.3,<21.0.0)
Requires-Dist: zipp (>=3.19.2,<4.0.0)
Project-URL: Repository, https://github.com/miracle-as/openknowit_ign8.git
